<?xml version="1.0" encoding="UTF-8" standalone="yes"?>
<w:document xmlns:o="urn:schemas-microsoft-com:office:office" xmlns:r="http://schemas.openxmlformats.org/officeDocument/2006/relationships" xmlns:v="urn:schemas-microsoft-com:vml" xmlns:w="http://schemas.openxmlformats.org/wordprocessingml/2006/main" xmlns:w10="urn:schemas-microsoft-com:office:word" xmlns:wp="http://schemas.openxmlformats.org/drawingml/2006/wordprocessingDrawing" xmlns:pic="http://schemas.openxmlformats.org/drawingml/2006/picture" xmlns:wps="http://schemas.microsoft.com/office/word/2010/wordprocessingShape" xmlns:wpg="http://schemas.microsoft.com/office/word/2010/wordprocessingGroup" xmlns:mc="http://schemas.openxmlformats.org/markup-compatibility/2006" xmlns:wp14="http://schemas.microsoft.com/office/word/2010/wordprocessingDrawing" xmlns:w14="http://schemas.microsoft.com/office/word/2010/wordml" xmlns:w15="http://schemas.microsoft.com/office/word/2012/wordml" mc:Ignorable="w14 wp14 w15"><w:body><w:p><w:pPr><w:pStyle w:val="Normal"/><w:bidi w:val="0"/><w:jc w:val="start"/><w:rPr></w:rPr></w:pPr><w:r><w:rPr></w:rPr><mc:AlternateContent><mc:Choice Requires="wps"><w:drawing><wp:anchor distT="0" distB="0" distL="0" distR="0" simplePos="0" relativeHeight="2" behindDoc="1" locked="0" layoutInCell="0" allowOverlap="1"><wp:simplePos x="0" y="0"/><wp:positionH relativeFrom="column"><wp:posOffset>721360</wp:posOffset></wp:positionH><wp:positionV relativeFrom="paragraph"><wp:posOffset>522605</wp:posOffset></wp:positionV><wp:extent cx="984250" cy="351790"/><wp:effectExtent l="0" t="0" r="0" b="0"/><wp:wrapSquare wrapText="bothSides"/><wp:docPr id="1" name="Shape1"></wp:docPr><a:graphic xmlns:a="http://schemas.openxmlformats.org/drawingml/2006/main"><a:graphicData uri="http://schemas.microsoft.com/office/word/2010/wordprocessingShape"><wps:wsp><wps:cNvSpPr txBox="1"/><wps:spPr><a:xfrm><a:off x="0" y="0"/><a:ext cx="984240" cy="351720"/></a:xfrm><a:prstGeom prst="rect"><a:avLst/></a:prstGeom><a:noFill/><a:ln w="0"><a:noFill/></a:ln></wps:spPr><wps:txbx><w:txbxContent><w:p><w:pPr><w:overflowPunct w:val="false"/><w:bidi w:val="0"/><w:rPr></w:rPr></w:pPr><w:r><w:rPr><w:rFonts w:ascii="Liberation Sans" w:hAnsi="Liberation Sans" w:eastAsia="Liberation Sans" w:cs="Liberation Sans"/><w:b/><w:bCs/><w:color w:val="000000"/><w:sz w:val="48"/><w:szCs w:val="48"/></w:rPr><w:t>Page 1</w:t></w:r></w:p></w:txbxContent></wps:txbx><wps:bodyPr wrap="square" lIns="0" tIns="0" rIns="0" bIns="0" anchor="t"><a:noAutofit/></wps:bodyPr></wps:wsp></a:graphicData></a:graphic></wp:anchor></w:drawing></mc:Choice><mc:Fallback><w:pict><v:shapetype id="_x0000_t202" coordsize="21600,21600" o:spt="202" path="m,l,21600l21600,21600l21600,xe"><v:stroke joinstyle="miter"/><v:path gradientshapeok="t" o:connecttype="rect"/></v:shapetype><v:shape id="shape_0" stroked="f" o:allowincell="f" style="position:absolute;margin-left:56.8pt;margin-top:41.15pt;width:77.45pt;height:27.65pt;mso-wrap-style:none;v-text-anchor:top" type="_x0000_t202"><v:textbox><w:txbxContent><w:p><w:pPr><w:overflowPunct w:val="false"/><w:bidi w:val="0"/><w:rPr></w:rPr></w:pPr><w:r><w:rPr><w:rFonts w:ascii="Liberation Sans" w:hAnsi="Liberation Sans" w:eastAsia="Liberation Sans" w:cs="Liberation Sans"/><w:b/><w:bCs/><w:color w:val="000000"/><w:sz w:val="48"/><w:szCs w:val="48"/></w:rPr><w:t>Page 1</w:t></w:r></w:p></w:txbxContent></v:textbox><v:fill o:detectmouseclick="t" on="false"/><v:stroke color="#3465a4" joinstyle="round" endcap="flat"/><w10:wrap type="square"/></v:shape></w:pict></mc:Fallback></mc:AlternateContent><mc:AlternateContent><mc:Choice Requires="wps"><w:drawing><wp:anchor distT="0" distB="0" distL="0" distR="0" simplePos="0" relativeHeight="3" behindDoc="1" locked="0" layoutInCell="0" allowOverlap="1"><wp:simplePos x="0" y="0"/><wp:positionH relativeFrom="column"><wp:posOffset>721360</wp:posOffset></wp:positionH><wp:positionV relativeFrom="paragraph"><wp:posOffset>1049020</wp:posOffset></wp:positionV><wp:extent cx="1567180" cy="175895"/><wp:effectExtent l="0" t="0" r="0" b="0"/><wp:wrapSquare wrapText="bothSides"/><wp:docPr id="2" name="Shape2"></wp:docPr><a:graphic xmlns:a="http://schemas.openxmlformats.org/drawingml/2006/main"><a:graphicData uri="http://schemas.microsoft.com/office/word/2010/wordprocessingShape"><wps:wsp><wps:cNvSpPr txBox="1"/><wps:spPr><a:xfrm><a:off x="0" y="0"/><a:ext cx="1567080" cy="176040"/></a:xfrm><a:prstGeom prst="rect"><a:avLst/></a:prstGeom><a:noFill/><a:ln w="0"><a:noFill/></a:ln></wps:spPr><wps:txbx><w:txbxContent><w:p><w:pPr><w:overflowPunct w:val="false"/><w:bidi w:val="0"/><w:rPr></w:rPr></w:pPr><w:r><w:rPr><w:rFonts w:ascii="Liberation Serif" w:hAnsi="Liberation Serif" w:eastAsia="Liberation Serif" w:cs="Liberation Serif"/><w:b w:val="false"/><w:bCs w:val="false"/><w:color w:val="000000"/><w:sz w:val="24"/><w:szCs w:val="24"/></w:rPr><w:t>This is content on page 1.</w:t></w:r></w:p></w:txbxContent></wps:txbx><wps:bodyPr wrap="square" lIns="0" tIns="0" rIns="0" bIns="0" anchor="t"><a:noAutofit/></wps:bodyPr></wps:wsp></a:graphicData></a:graphic></wp:anchor></w:drawing></mc:Choice><mc:Fallback><w:pict><v:shape id="shape_0" stroked="f" o:allowincell="f" style="position:absolute;margin-left:56.8pt;margin-top:82.6pt;width:123.35pt;height:13.8pt;mso-wrap-style:none;v-text-anchor:top" type="_x0000_t202"><v:textbox><w:txbxContent><w:p><w:pPr><w:overflowPunct w:val="false"/><w:bidi w:val="0"/><w:rPr></w:rPr></w:pPr><w:r><w:rPr><w:rFonts w:ascii="Liberation Serif" w:hAnsi="Liberation Serif" w:eastAsia="Liberation Serif" w:cs="Liberation Serif"/><w:b w:val="false"/><w:bCs w:val="false"/><w:color w:val="000000"/><w:sz w:val="24"/><w:szCs w:val="24"/></w:rPr><w:t>This is content on page 1.</w:t></w:r></w:p></w:txbxContent></v:textbox><v:fill o:detectmouseclick="t" on="false"/><v:stroke color="#3465a4" joinstyle="round" endcap="flat"/><w10:wrap type="square"/></v:shape></w:pict></mc:Fallback></mc:AlternateContent><mc:AlternateContent><mc:Choice Requires="wps"><w:drawing><wp:anchor distT="0" distB="0" distL="0" distR="0" simplePos="0" relativeHeight="4" behindDoc="1" locked="0" layoutInCell="0" allowOverlap="1"><wp:simplePos x="0" y="0"/><wp:positionH relativeFrom="column"><wp:posOffset>721360</wp:posOffset></wp:positionH><wp:positionV relativeFrom="paragraph"><wp:posOffset>1560195</wp:posOffset></wp:positionV><wp:extent cx="984250" cy="351790"/><wp:effectExtent l="0" t="0" r="0" b="0"/><wp:wrapSquare wrapText="bothSides"/><wp:docPr id="3" name="Shape3"></wp:docPr><a:graphic xmlns:a="http://schemas.openxmlformats.org/drawingml/2006/main"><a:graphicData uri="http://schemas.microsoft.com/office/word/2010/wordprocessingShape"><wps:wsp><wps:cNvSpPr txBox="1"/><wps:spPr><a:xfrm><a:off x="0" y="0"/><a:ext cx="984240" cy="351720"/></a:xfrm><a:prstGeom prst="rect"><a:avLst/></a:prstGeom><a:noFill/><a:ln w="0"><a:noFill/></a:ln></wps:spPr><wps:txbx><w:txbxContent><w:p><w:pPr><w:overflowPunct w:val="false"/><w:bidi w:val="0"/><w:rPr></w:rPr></w:pPr><w:r><w:rPr><w:rFonts w:ascii="Liberation Sans" w:hAnsi="Liberation Sans" w:eastAsia="Liberation Sans" w:cs="Liberation Sans"/><w:b/><w:bCs/><w:color w:val="000000"/><w:sz w:val="48"/><w:szCs w:val="48"/></w:rPr><w:t>Page 2</w:t></w:r></w:p></w:txbxContent></wps:txbx><wps:bodyPr wrap="square" lIns="0" tIns="0" rIns="0" bIns="0" anchor="t"><a:noAutofit/></wps:bodyPr></wps:wsp></a:graphicData></a:graphic></wp:anchor></w:drawing></mc:Choice><mc:Fallback><w:pict><v:shape id="shape_0" stroked="f" o:allowincell="f" style="position:absolute;margin-left:56.8pt;margin-top:122.85pt;width:77.45pt;height:27.65pt;mso-wrap-style:none;v-text-anchor:top" type="_x0000_t202"><v:textbox><w:txbxContent><w:p><w:pPr><w:overflowPunct w:val="false"/><w:bidi w:val="0"/><w:rPr></w:rPr></w:pPr><w:r><w:rPr><w:rFonts w:ascii="Liberation Sans" w:hAnsi="Liberation Sans" w:eastAsia="Liberation Sans" w:cs="Liberation Sans"/><w:b/><w:bCs/><w:color w:val="000000"/><w:sz w:val="48"/><w:szCs w:val="48"/></w:rPr><w:t>Page 2</w:t></w:r></w:p></w:txbxContent></v:textbox><v:fill o:detectmouseclick="t" on="false"/><v:stroke color="#3465a4" joinstyle="round" endcap="flat"/><w10:wrap type="square"/></v:shape></w:pict></mc:Fallback></mc:AlternateContent><mc:AlternateContent><mc:Choice Requires="wps"><w:drawing><wp:anchor distT="0" distB="0" distL="0" distR="0" simplePos="0" relativeHeight="5" behindDoc="1" locked="0" layoutInCell="0" allowOverlap="1"><wp:simplePos x="0" y="0"/><wp:positionH relativeFrom="column"><wp:posOffset>721360</wp:posOffset></wp:positionH><wp:positionV relativeFrom="paragraph"><wp:posOffset>2086610</wp:posOffset></wp:positionV><wp:extent cx="1567180" cy="175895"/><wp:effectExtent l="0" t="0" r="0" b="0"/><wp:wrapSquare wrapText="bothSides"/><wp:docPr id="4" name="Shape4"></wp:docPr><a:graphic xmlns:a="http://schemas.openxmlformats.org/drawingml/2006/main"><a:graphicData uri="http://schemas.microsoft.com/office/word/2010/wordprocessingShape"><wps:wsp><wps:cNvSpPr txBox="1"/><wps:spPr><a:xfrm><a:off x="0" y="0"/><a:ext cx="1567080" cy="176040"/></a:xfrm><a:prstGeom prst="rect"><a:avLst/></a:prstGeom><a:noFill/><a:ln w="0"><a:noFill/></a:ln></wps:spPr><wps:txbx><w:txbxContent><w:p><w:pPr><w:overflowPunct w:val="false"/><w:bidi w:val="0"/><w:rPr></w:rPr></w:pPr><w:r><w:rPr><w:rFonts w:ascii="Liberation Serif" w:hAnsi="Liberation Serif" w:eastAsia="Liberation Serif" w:cs="Liberation Serif"/><w:b w:val="false"/><w:bCs w:val="false"/><w:color w:val="000000"/><w:sz w:val="24"/><w:szCs w:val="24"/></w:rPr><w:t>This is content on page 2.</w:t></w:r></w:p></w:txbxContent></wps:txbx><wps:bodyPr wrap="square" lIns="0" tIns="0" rIns="0" bIns="0" anchor="t"><a:noAutofit/></wps:bodyPr></wps:wsp></a:graphicData></a:graphic></wp:anchor></w:drawing></mc:Choice><mc:Fallback><w:pict><v:shape id="shape_0" stroked="f" o:allowincell="f" style="position:absolute;margin-left:56.8pt;margin-top:164.3pt;width:123.35pt;height:13.8pt;mso-wrap-style:none;v-text-anchor:top" type="_x0000_t202"><v:textbox><w:txbxContent><w:p><w:pPr><w:overflowPunct w:val="false"/><w:bidi w:val="0"/><w:rPr></w:rPr></w:pPr><w:r><w:rPr><w:rFonts w:ascii="Liberation Serif" w:hAnsi="Liberation Serif" w:eastAsia="Liberation Serif" w:cs="Liberation Serif"/><w:b w:val="false"/><w:bCs w:val="false"/><w:color w:val="000000"/><w:sz w:val="24"/><w:szCs w:val="24"/></w:rPr><w:t>This is content on page 2.</w:t></w:r></w:p></w:txbxContent></v:textbox><v:fill o:detectmouseclick="t" on="false"/><v:stroke color="#3465a4" joinstyle="round" endcap="flat"/><w10:wrap type="square"/></v:shape></w:pict></mc:Fallback></mc:AlternateContent><mc:AlternateContent><mc:Choice Requires="wps"><w:drawing><wp:anchor distT="0" distB="0" distL="0" distR="0" simplePos="0" relativeHeight="6" behindDoc="1" locked="0" layoutInCell="0" allowOverlap="1"><wp:simplePos x="0" y="0"/><wp:positionH relativeFrom="column"><wp:posOffset>721360</wp:posOffset></wp:positionH><wp:positionV relativeFrom="paragraph"><wp:posOffset>2598420</wp:posOffset></wp:positionV><wp:extent cx="984250" cy="351790"/><wp:effectExtent l="0" t="0" r="0" b="0"/><wp:wrapSquare wrapText="bothSides"/><wp:docPr id="5" name="Shape5"></wp:docPr><a:graphic xmlns:a="http://schemas.openxmlformats.org/drawingml/2006/main"><a:graphicData uri="http://schemas.microsoft.com/office/word/2010/wordprocessingShape"><wps:wsp><wps:cNvSpPr txBox="1"/><wps:spPr><a:xfrm><a:off x="0" y="0"/><a:ext cx="984240" cy="351720"/></a:xfrm><a:prstGeom prst="rect"><a:avLst/></a:prstGeom><a:noFill/><a:ln w="0"><a:noFill/></a:ln></wps:spPr><wps:txbx><w:txbxContent><w:p><w:pPr><w:overflowPunct w:val="false"/><w:bidi w:val="0"/><w:rPr></w:rPr></w:pPr><w:r><w:rPr><w:rFonts w:ascii="Liberation Sans" w:hAnsi="Liberation Sans" w:eastAsia="Liberation Sans" w:cs="Liberation Sans"/><w:b/><w:bCs/><w:color w:val="000000"/><w:sz w:val="48"/><w:szCs w:val="48"/></w:rPr><w:t>Page 3</w:t></w:r></w:p></w:txbxContent></wps:txbx><wps:bodyPr wrap="square" lIns="0" tIns="0" rIns="0" bIns="0" anchor="t"><a:noAutofit/></wps:bodyPr></wps:wsp></a:graphicData></a:graphic></wp:anchor></w:drawing></mc:Choice><mc:Fallback><w:pict><v:shape id="shape_0" stroked="f" o:allowincell="f" style="position:absolute;margin-left:56.8pt;margin-top:204.6pt;width:77.45pt;height:27.65pt;mso-wrap-style:none;v-text-anchor:top" type="_x0000_t202"><v:textbox><w:txbxContent><w:p><w:pPr><w:overflowPunct w:val="false"/><w:bidi w:val="0"/><w:rPr></w:rPr></w:pPr><w:r><w:rPr><w:rFonts w:ascii="Liberation Sans" w:hAnsi="Liberation Sans" w:eastAsia="Liberation Sans" w:cs="Liberation Sans"/><w:b/><w:bCs/><w:color w:val="000000"/><w:sz w:val="48"/><w:szCs w:val="48"/></w:rPr><w:t>Page 3</w:t></w:r></w:p></w:txbxContent></v:textbox><v:fill o:detectmouseclick="t" on="false"/><v:stroke color="#3465a4" joinstyle="round" endcap="flat"/><w10:wrap type="square"/></v:shape></w:pict></mc:Fallback></mc:AlternateContent><mc:AlternateContent><mc:Choice Requires="wps"><w:drawing><wp:anchor distT="0" distB="0" distL="0" distR="0" simplePos="0" relativeHeight="7" behindDoc="1" locked="0" layoutInCell="0" allowOverlap="1"><wp:simplePos x="0" y="0"/><wp:positionH relativeFrom="column"><wp:posOffset>721360</wp:posOffset></wp:positionH><wp:positionV relativeFrom="paragraph"><wp:posOffset>3124200</wp:posOffset></wp:positionV><wp:extent cx="1567180" cy="175895"/><wp:effectExtent l="0" t="0" r="0" b="0"/><wp:wrapSquare wrapText="bothSides"/><wp:docPr id="6" name="Shape6"></wp:docPr><a:graphic xmlns:a="http://schemas.openxmlformats.org/drawingml/2006/main"><a:graphicData uri="http://schemas.microsoft.com/office/word/2010/wordprocessingShape"><wps:wsp><wps:cNvSpPr txBox="1"/><wps:spPr><a:xfrm><a:off x="0" y="0"/><a:ext cx="1567080" cy="176040"/></a:xfrm><a:prstGeom prst="rect"><a:avLst/></a:prstGeom><a:noFill/><a:ln w="0"><a:noFill/></a:ln></wps:spPr><wps:txbx><w:txbxContent><w:p><w:pPr><w:overflowPunct w:val="false"/><w:bidi w:val="0"/><w:rPr></w:rPr></w:pPr><w:r><w:rPr><w:rFonts w:ascii="Liberation Serif" w:hAnsi="Liberation Serif" w:eastAsia="Liberation Serif" w:cs="Liberation Serif"/><w:b w:val="false"/><w:bCs w:val="false"/><w:color w:val="000000"/><w:sz w:val="24"/><w:szCs w:val="24"/></w:rPr><w:t>This is content on page 3.</w:t></w:r></w:p></w:txbxContent></wps:txbx><wps:bodyPr wrap="square" lIns="0" tIns="0" rIns="0" bIns="0" anchor="t"><a:noAutofit/></wps:bodyPr></wps:wsp></a:graphicData></a:graphic></wp:anchor></w:drawing></mc:Choice><mc:Fallback><w:pict><v:shape id="shape_0" stroked="f" o:allowincell="f" style="position:absolute;margin-left:56.8pt;margin-top:246pt;width:123.35pt;height:13.8pt;mso-wrap-style:none;v-text-anchor:top" type="_x0000_t202"><v:textbox><w:txbxContent><w:p><w:pPr><w:overflowPunct w:val="false"/><w:bidi w:val="0"/><w:rPr></w:rPr></w:pPr><w:r><w:rPr><w:rFonts w:ascii="Liberation Serif" w:hAnsi="Liberation Serif" w:eastAsia="Liberation Serif" w:cs="Liberation Serif"/><w:b w:val="false"/><w:bCs w:val="false"/><w:color w:val="000000"/><w:sz w:val="24"/><w:szCs w:val="24"/></w:rPr><w:t>This is content on page 3.</w:t></w:r></w:p></w:txbxContent></v:textbox><v:fill o:detectmouseclick="t" on="false"/><v:stroke color="#3465a4" joinstyle="round" endcap="flat"/><w10:wrap type="square"/></v:shape></w:pict></mc:Fallback></mc:AlternateContent></w:r></w:p><w:sectPr><w:type w:val="nextPage"/><w:pgSz w:w="11906" w:h="16838"/><w:pgMar w:left="567" w:right="567" w:gutter="0" w:header="0" w:top="567" w:footer="0" w:bottom="567"/><w:pgNumType w:fmt="decimal"/><w:formProt w:val="false"/><w:textDirection w:val="lrTb"/><w:docGrid w:type="default" w:linePitch="600" w:charSpace="32768"/></w:sectPr></w:body></w:document>